<?xml version="1.0" encoding="UTF-8" ?>
<!DOCTYPE ldml SYSTEM "../../common/dtd/ldml.dtd">
<!-- Copyright © 1991-2025 Unicode, Inc.
For terms of use, see http://www.unicode.org/copyright.html
SPDX-License-Identifier: Unicode-3.0
CLDR data files are interpreted according to the LDML specification (http://unicode.org/reports/tr35/)
-->
<ldml>
	<identity>
		<version number="$Revision$"/>
		<language type="pap"/>
	</identity>
	<localeDisplayNames>
		<languages>
			<language type="ar" draft="unconfirmed">arabir</language>
			<language type="ar_001" draft="unconfirmed">arabir (mundu)</language>
			<language type="de" draft="unconfirmed">alemán</language>
			<language type="en" draft="unconfirmed">ingles</language>
			<language type="es" draft="unconfirmed">spañó</language>
			<language type="es_419" draft="unconfirmed">spañó di latino amérika</language>
			<language type="fr" draft="unconfirmed">franses</language>
			<language type="he" draft="unconfirmed">hebreo</language>
			<language type="hi" draft="unconfirmed">hindi</language>
			<language type="hmn" draft="unconfirmed">hmong</language>
			<language type="ht" draft="unconfirmed">kreol di Haiti</language>
			<language type="hz" draft="unconfirmed">herero</language>
			<language type="id" draft="unconfirmed">indones</language>
			<language type="it" draft="unconfirmed">italiano</language>
			<language type="ja" draft="unconfirmed">hapones</language>
			<language type="ko" draft="unconfirmed">koreano</language>
			<language type="la" draft="unconfirmed">latin</language>
			<language type="nl" draft="unconfirmed">hulandes</language>
			<language type="pap">Papiamentu</language>
			<language type="pl" draft="unconfirmed">polaco</language>
			<language type="pt" draft="unconfirmed">portugues</language>
			<language type="ru" draft="unconfirmed">ruso</language>
			<language type="th" draft="unconfirmed">tailandes</language>
			<language type="tr" draft="unconfirmed">turko</language>
			<language type="und" draft="unconfirmed">idioma deskonosí</language>
			<language type="zh" draft="unconfirmed">chines</language>
		</languages>
		<scripts>
			<script type="Arab" draft="unconfirmed">Arabir</script>
			<script type="Brai" draft="unconfirmed">braille</script>
			<script type="Jpan" draft="unconfirmed">hapones</script>
			<script type="Kore" draft="unconfirmed">koreano</script>
			<script type="Latn" draft="unconfirmed">Latin</script>
			<script type="Zxxx" draft="unconfirmed">No Tin Ortografia</script>
			<script type="Zzzz" draft="unconfirmed">Ortografia Deskonosí</script>
		</scripts>
		<territories>
			<territory type="001" draft="unconfirmed">mundu</territory>
			<territory type="002" draft="unconfirmed">Áfrika</territory>
			<territory type="003" draft="unconfirmed">Nort Amérika</territory>
			<territory type="005" draft="unconfirmed">Zùit Amérika</territory>
			<territory type="011" draft="unconfirmed">Wèst Afrika</territory>
			<territory type="013" draft="unconfirmed">Amérika Sentral</territory>
			<territory type="014" draft="unconfirmed">Ost Afrika</territory>
			<territory type="015" draft="unconfirmed">Nort Afrika</territory>
			<territory type="017" draft="unconfirmed">Afrika Sentral</territory>
			<territory type="018" draft="unconfirmed">Zùit Afrika</territory>
			<territory type="019" draft="unconfirmed">Amérika</territory>
			<territory type="021" draft="unconfirmed">Parti Nort di Amérika</territory>
			<territory type="029" draft="unconfirmed">Karibe</territory>
			<territory type="030" draft="unconfirmed">Ost Asia</territory>
			<territory type="034" draft="unconfirmed">Zùit Asia</territory>
			<territory type="035" draft="unconfirmed">Zùitost Asia</territory>
			<territory type="039" draft="unconfirmed">Zùit Europa</territory>
			<territory type="053" draft="unconfirmed">Australasia</territory>
			<territory type="054" draft="unconfirmed">Melanesia</territory>
			<territory type="057" draft="unconfirmed">Region di Micronesia</territory>
			<territory type="061" draft="unconfirmed">Polinesia</territory>
			<territory type="142" draft="unconfirmed">Asia</territory>
			<territory type="143" draft="unconfirmed">Asia Sentral</territory>
			<territory type="145" draft="unconfirmed">Wèst Asia</territory>
			<territory type="150" draft="unconfirmed">Europa</territory>
			<territory type="151" draft="unconfirmed">Ost Europa</territory>
			<territory type="154" draft="unconfirmed">Nort Europa</territory>
			<territory type="155" draft="unconfirmed">Wèst Europa</territory>
			<territory type="419" draft="unconfirmed">Latino Amérika</territory>
			<territory type="AF" draft="unconfirmed">Afghanistan</territory>
			<territory type="AG" draft="unconfirmed">Antigua &amp; Barbuda</territory>
			<territory type="AI" draft="unconfirmed">Anguilla</territory>
			<territory type="AL" draft="unconfirmed">Albania</territory>
			<territory type="AO" draft="unconfirmed">Angola</territory>
			<territory type="AR" draft="unconfirmed">Argentina</territory>
			<territory type="AT" draft="unconfirmed">Austria</territory>
			<territory type="AU" draft="unconfirmed">Australia</territory>
			<territory type="AW" draft="unconfirmed">Aruba</territory>
			<territory type="BA" draft="unconfirmed">Bosnia i Herzegowina</territory>
			<territory type="BB" draft="unconfirmed">Barbados</territory>
			<territory type="BE" draft="unconfirmed">Bèlgika</territory>
			<territory type="BG" draft="unconfirmed">Bulgaria</territory>
			<territory type="BL" draft="unconfirmed">Saint Bathélemy</territory>
			<territory type="BM" draft="unconfirmed">Bermuda</territory>
			<territory type="BO" draft="unconfirmed">Bolivia</territory>
			<territory type="BQ" draft="unconfirmed">Antia Hulandes</territory>
			<territory type="BR" draft="unconfirmed">Brazil</territory>
			<territory type="BS" draft="unconfirmed">Bahamas</territory>
			<territory type="BV" draft="unconfirmed">Isla Bouvet</territory>
			<territory type="BW" draft="unconfirmed">Botswana</territory>
			<territory type="BY" draft="unconfirmed">Belarus</territory>
			<territory type="BZ" draft="unconfirmed">Belize</territory>
			<territory type="CA" draft="unconfirmed">Canada</territory>
			<territory type="CD" draft="unconfirmed">Congo - Kinshasa</territory>
			<territory type="CF" draft="unconfirmed">Repúblika Sentroafrikano</territory>
			<territory type="CG" draft="unconfirmed">Congo - Brazzaville</territory>
			<territory type="CG" alt="variant" draft="unconfirmed">Congo (Repúblika)</territory>
			<territory type="CH" draft="unconfirmed">Suisa</territory>
			<territory type="CI" draft="unconfirmed">Côte d’Ivoire</territory>
			<territory type="CL" draft="unconfirmed">Chile</territory>
			<territory type="CM" draft="unconfirmed">Camerun</territory>
			<territory type="CN" draft="unconfirmed">China</territory>
			<territory type="CO" draft="unconfirmed">Colombia</territory>
			<territory type="CR" draft="unconfirmed">Costa Rica</territory>
			<territory type="CU" draft="unconfirmed">Cuba</territory>
			<territory type="CV" draft="unconfirmed">Kabo Verde</territory>
			<territory type="CW">Kòrsou</territory>
			<territory type="CZ" draft="unconfirmed">Cheko</territory>
			<territory type="CZ" alt="variant" draft="unconfirmed">Repúblika di Cheko</territory>
			<territory type="DE" draft="unconfirmed">Alemania</territory>
			<territory type="DK" draft="unconfirmed">Dinamarka</territory>
			<territory type="DM" draft="unconfirmed">Dominica</territory>
			<territory type="DO" draft="unconfirmed">Repúblika Dominikano</territory>
			<territory type="DZ" draft="unconfirmed">Algeria</territory>
			<territory type="EC" draft="unconfirmed">Ecuador</territory>
			<territory type="EE" draft="unconfirmed">Estonia</territory>
			<territory type="EG" draft="unconfirmed">Egipto</territory>
			<territory type="EH" draft="unconfirmed">Western Sahara</territory>
			<territory type="ER" draft="unconfirmed">Eritrea</territory>
			<territory type="ES" draft="unconfirmed">Spaña</territory>
			<territory type="ET" draft="unconfirmed">Etiopia</territory>
			<territory type="EU" draft="unconfirmed">Union Europeo</territory>
			<territory type="FI" draft="unconfirmed">Finlandia</territory>
			<territory type="FJ" draft="unconfirmed">Fiji</territory>
			<territory type="FK" draft="unconfirmed">Islanan Falkland</territory>
			<territory type="FK" alt="variant" draft="unconfirmed">Islanan Falkland (Islas Malvinas)</territory>
			<territory type="FM" draft="unconfirmed">Micronesia</territory>
			<territory type="FR" draft="unconfirmed">Fransia</territory>
			<territory type="GB" draft="unconfirmed">Gran Bretaña</territory>
			<territory type="GD" draft="unconfirmed">Grenada</territory>
			<territory type="GF" draft="unconfirmed">Guyana Franses</territory>
			<territory type="GH" draft="unconfirmed">Ghana</territory>
			<territory type="GL" draft="unconfirmed">Grunlandia</territory>
			<territory type="GM" draft="unconfirmed">Gambia</territory>
			<territory type="GN" draft="unconfirmed">Guinea</territory>
			<territory type="GP" draft="unconfirmed">Guadeloupe</territory>
			<territory type="GQ" draft="unconfirmed">Guinea Ekuatorial</territory>
			<territory type="GR" draft="unconfirmed">Gresia</territory>
			<territory type="GT" draft="unconfirmed">Guatemala</territory>
			<territory type="GU" draft="unconfirmed">Guam</territory>
			<territory type="GW" draft="unconfirmed">Guinea-Bissau</territory>
			<territory type="GY" draft="unconfirmed">Guyana</territory>
			<territory type="HK" draft="unconfirmed">Hong Kong</territory>
			<territory type="HN" draft="unconfirmed">Honduras</territory>
			<territory type="HR" draft="unconfirmed">Kroasia</territory>
			<territory type="HT" draft="unconfirmed">Haiti</territory>
			<territory type="HU" draft="unconfirmed">Hungria</territory>
			<territory type="ID" draft="unconfirmed">Indonesia</territory>
			<territory type="IE" draft="unconfirmed">Irlanda</territory>
			<territory type="IL" draft="unconfirmed">Israel</territory>
			<territory type="IN" draft="unconfirmed">India</territory>
			<territory type="IQ" draft="unconfirmed">Irak</territory>
			<territory type="IR" draft="unconfirmed">Iran</territory>
			<territory type="IS" draft="unconfirmed">Islandia</territory>
			<territory type="IT" draft="unconfirmed">Italia</territory>
			<territory type="JM" draft="unconfirmed">Jamaica</territory>
			<territory type="JP" draft="unconfirmed">Hapon</territory>
			<territory type="KE" draft="unconfirmed">Kenya</territory>
			<territory type="KH" draft="unconfirmed">Cambodia</territory>
			<territory type="KM" draft="unconfirmed">Comóros</territory>
			<territory type="KN" draft="unconfirmed">St. Kitts i Nevis</territory>
			<territory type="KP" draft="unconfirmed">Nort Korea</territory>
			<territory type="KR" draft="unconfirmed">Surkorea</territory>
			<territory type="KY" draft="unconfirmed">Islanan Caiman</territory>
			<territory type="LC" draft="unconfirmed">Sint Lucia</territory>
			<territory type="LI" draft="unconfirmed">Liechtenstein</territory>
			<territory type="LK" draft="unconfirmed">Sri Lanka</territory>
			<territory type="LR" draft="unconfirmed">Liberia</territory>
			<territory type="LU" draft="unconfirmed">Luxemburg</territory>
			<territory type="MA" draft="unconfirmed">Morocco</territory>
			<territory type="MC" draft="unconfirmed">Monaco</territory>
			<territory type="MD" draft="unconfirmed">Moldavia</territory>
			<territory type="ME" draft="unconfirmed">Montenegro</territory>
			<territory type="MF" draft="unconfirmed">Saint Martin</territory>
			<territory type="MG" draft="unconfirmed">Madagascar</territory>
			<territory type="ML" draft="unconfirmed">Mali</territory>
			<territory type="MN" draft="unconfirmed">Mongolia</territory>
			<territory type="MO" draft="unconfirmed">Macao</territory>
			<territory type="MQ" draft="unconfirmed">Martinique</territory>
			<territory type="MS" draft="unconfirmed">Montserrat</territory>
			<territory type="MT" draft="unconfirmed">Malta</territory>
			<territory type="MV" draft="unconfirmed">Maldives</territory>
			<territory type="MW" draft="unconfirmed">Malawi</territory>
			<territory type="MX" draft="unconfirmed">México</territory>
			<territory type="MZ" draft="unconfirmed">Mozambique</territory>
			<territory type="NE" draft="unconfirmed">Niger</territory>
			<territory type="NG" draft="unconfirmed">Nigeria</territory>
			<territory type="NI" draft="unconfirmed">Nicaragua</territory>
			<territory type="NL" draft="unconfirmed">Hulanda</territory>
			<territory type="NO" draft="unconfirmed">Noruega</territory>
			<territory type="NP" draft="unconfirmed">Nepal</territory>
			<territory type="PA" draft="unconfirmed">Panamá</territory>
			<territory type="PE" draft="unconfirmed">Perú</territory>
			<territory type="PF" draft="unconfirmed">Polinesia Franses</territory>
			<territory type="PH" draft="unconfirmed">Filipinas</territory>
			<territory type="PL" draft="unconfirmed">Polonia</territory>
			<territory type="PM" draft="unconfirmed">St. Pierre &amp; Miquelon</territory>
			<territory type="PR" draft="unconfirmed">Puerto Rico</territory>
			<territory type="PT" draft="unconfirmed">Portugal</territory>
			<territory type="PY" draft="unconfirmed">Paraguay</territory>
			<territory type="QA" draft="unconfirmed">Qatar</territory>
			<territory type="RO" draft="unconfirmed">Romania</territory>
			<territory type="RS" draft="unconfirmed">Servia</territory>
			<territory type="RU" draft="unconfirmed">Rusia</territory>
			<territory type="RW" draft="unconfirmed">Rwanda</territory>
			<territory type="SC" draft="unconfirmed">Seychelles</territory>
			<territory type="SD" draft="unconfirmed">Sudan</territory>
			<territory type="SE" draft="unconfirmed">Suesia</territory>
			<territory type="SG" draft="unconfirmed">Singapore</territory>
			<territory type="SH" draft="unconfirmed">Sint Helena</territory>
			<territory type="SI" draft="unconfirmed">Slovenia</territory>
			<territory type="SK" draft="unconfirmed">Slovakia</territory>
			<territory type="SL" draft="unconfirmed">Sierra Leone</territory>
			<territory type="SM" draft="unconfirmed">San Marino</territory>
			<territory type="SN" draft="unconfirmed">Senegal</territory>
			<territory type="SO" draft="unconfirmed">Somalia</territory>
			<territory type="SR" draft="unconfirmed">Surinam</territory>
			<territory type="SV" draft="unconfirmed">El Salvador</territory>
			<territory type="SX" draft="unconfirmed">Sint Maarten</territory>
			<territory type="TC" draft="unconfirmed">Turks i Caicos</territory>
			<territory type="TD" draft="unconfirmed">Chad</territory>
			<territory type="TH" draft="unconfirmed">Tailandia</territory>
			<territory type="TR" draft="unconfirmed">Turkia</territory>
			<territory type="TT" draft="unconfirmed">Trinidad i Tobago</territory>
			<territory type="TW" draft="unconfirmed">Taiwan</territory>
			<territory type="UA" draft="unconfirmed">Ukrania</territory>
			<territory type="UG" draft="unconfirmed">Uganda</territory>
			<territory type="UN" draft="unconfirmed">Nashonnan Uní</territory>
			<territory type="US" draft="unconfirmed">Merka</territory>
			<territory type="UY" draft="unconfirmed">Uruguay</territory>
			<territory type="VC" draft="unconfirmed">Sint Vicent i Grenadines</territory>
			<territory type="VE" draft="unconfirmed">Venezuela</territory>
			<territory type="VG" draft="unconfirmed">Virgin Islands (Britániko)</territory>
			<territory type="VI" draft="unconfirmed">Virgin Islands (Merikano)</territory>
			<territory type="VN" draft="unconfirmed">Vietnam</territory>
			<territory type="ZA" draft="unconfirmed">Suráfrika</territory>
			<territory type="ZM" draft="unconfirmed">Zambia</territory>
			<territory type="ZW" draft="unconfirmed">Zimbabwe</territory>
			<territory type="ZZ" draft="unconfirmed">Region Deskonosí</territory>
		</territories>
		<measurementSystemNames>
			<measurementSystemName type="metric" draft="unconfirmed">meter</measurementSystemName>
			<measurementSystemName type="UK" draft="unconfirmed">britániko</measurementSystemName>
			<measurementSystemName type="US" draft="unconfirmed">merikano</measurementSystemName>
		</measurementSystemNames>
		<codePatterns>
			<codePattern type="language" draft="unconfirmed">Idioma: {0}</codePattern>
			<codePattern type="script" draft="unconfirmed">Manera di skirbi: {0}</codePattern>
			<codePattern type="territory" draft="unconfirmed">Region: {0}</codePattern>
		</codePatterns>
	</localeDisplayNames>
	<characters>
		<exemplarCharacters>[a b c d eè f g h i j k l m nñ oò p q r s t uùü v w x y z]</exemplarCharacters>
		<exemplarCharacters type="auxiliary">[á é í ó ú]</exemplarCharacters>
		<exemplarCharacters type="punctuation">[\- ‑ , ; \: ! ? . … '‘’ &quot;“” ( ) \[ \] § @ / \&amp; # % ′ ″]</exemplarCharacters>
	</characters>
	<dates>
		<calendars>
			<calendar type="generic">
				<dateFormats>
					<dateFormatLength type="full">
						<dateFormat>
							<pattern draft="unconfirmed">EEEE, d MMMM y G</pattern>
						</dateFormat>
					</dateFormatLength>
					<dateFormatLength type="long">
						<dateFormat>
							<pattern draft="unconfirmed">d MMMM y G</pattern>
						</dateFormat>
					</dateFormatLength>
					<dateFormatLength type="medium">
						<dateFormat>
							<pattern draft="unconfirmed">d MMM y G</pattern>
						</dateFormat>
					</dateFormatLength>
					<dateFormatLength type="short">
						<dateFormat>
							<pattern draft="unconfirmed">dd-MM-y GGGGG</pattern>
						</dateFormat>
					</dateFormatLength>
				</dateFormats>
				<dateTimeFormats>
					<dateTimeFormatLength type="full">
						<dateTimeFormat>
							<pattern draft="unconfirmed">{1} {0}</pattern>
						</dateTimeFormat>
					</dateTimeFormatLength>
					<dateTimeFormatLength type="long">
						<dateTimeFormat>
							<pattern draft="unconfirmed">{1} {0}</pattern>
						</dateTimeFormat>
					</dateTimeFormatLength>
					<dateTimeFormatLength type="medium">
						<dateTimeFormat>
							<pattern draft="unconfirmed">{1} {0}</pattern>
						</dateTimeFormat>
						<dateTimeFormat type="atTime">
							<pattern draft="unconfirmed">{1}, {0}</pattern>
						</dateTimeFormat>
					</dateTimeFormatLength>
					<dateTimeFormatLength type="short">
						<dateTimeFormat>
							<pattern draft="unconfirmed">{1} {0}</pattern>
						</dateTimeFormat>
						<dateTimeFormat type="atTime">
							<pattern draft="unconfirmed">{1}, {0}</pattern>
						</dateTimeFormat>
					</dateTimeFormatLength>
					<availableFormats>
						<dateFormatItem id="Ed" draft="unconfirmed">E, d</dateFormatItem>
						<dateFormatItem id="Gy" draft="unconfirmed">y G</dateFormatItem>
						<dateFormatItem id="GyMd" draft="unconfirmed">dd-MM-y GGGGG</dateFormatItem>
						<dateFormatItem id="GyMMM" draft="unconfirmed">MMM y G</dateFormatItem>
						<dateFormatItem id="GyMMMd" draft="unconfirmed">d MMM y G</dateFormatItem>
						<dateFormatItem id="GyMMMEd" draft="unconfirmed">E, d MMM y G</dateFormatItem>
						<dateFormatItem id="Md" draft="unconfirmed">dd-MM</dateFormatItem>
						<dateFormatItem id="MEd" draft="unconfirmed">E, dd-MM</dateFormatItem>
						<dateFormatItem id="MMMd" draft="unconfirmed">d MMM</dateFormatItem>
						<dateFormatItem id="MMMEd" draft="unconfirmed">E, d MMM</dateFormatItem>
						<dateFormatItem id="MMMMd" draft="unconfirmed">d MMMM</dateFormatItem>
						<dateFormatItem id="y" draft="unconfirmed">y G</dateFormatItem>
						<dateFormatItem id="yyyy" draft="unconfirmed">y G</dateFormatItem>
						<dateFormatItem id="yyyyM" draft="unconfirmed">MM-y GGGGG</dateFormatItem>
						<dateFormatItem id="yyyyMd" draft="unconfirmed">dd-MM-y GGGGG</dateFormatItem>
						<dateFormatItem id="yyyyMEd" draft="unconfirmed">E, dd-MM-y GGGGG</dateFormatItem>
						<dateFormatItem id="yyyyMMM" draft="unconfirmed">MMM y G</dateFormatItem>
						<dateFormatItem id="yyyyMMMd" draft="unconfirmed">d MMM y G</dateFormatItem>
						<dateFormatItem id="yyyyMMMEd" draft="unconfirmed">E, d MMM y G</dateFormatItem>
						<dateFormatItem id="yyyyMMMM" draft="unconfirmed">MMMM y G</dateFormatItem>
						<dateFormatItem id="yyyyQQQ" draft="unconfirmed">QQQ y G</dateFormatItem>
						<dateFormatItem id="yyyyQQQQ" draft="unconfirmed">QQQQ y G</dateFormatItem>
					</availableFormats>
					<intervalFormats>
						<intervalFormatItem id="Gy">
							<greatestDifference id="G" draft="unconfirmed">y G – y G</greatestDifference>
							<greatestDifference id="y" draft="unconfirmed">y–y G</greatestDifference>
						</intervalFormatItem>
						<intervalFormatItem id="GyM">
							<greatestDifference id="G" draft="unconfirmed">MM-y-GGGGG – MM-y-GGGGG</greatestDifference>
							<greatestDifference id="M" draft="unconfirmed">MM-y – MM-y GGGGG</greatestDifference>
							<greatestDifference id="y" draft="unconfirmed">MM-y – MM-y GGGGG</greatestDifference>
						</intervalFormatItem>
						<intervalFormatItem id="GyMd">
							<greatestDifference id="d" draft="unconfirmed">dd-MM-y – dd-MM-y GGGGG</greatestDifference>
							<greatestDifference id="G" draft="unconfirmed">dd-MM-y GGGGG – dd-MM-y GGGGG</greatestDifference>
							<greatestDifference id="M" draft="unconfirmed">dd-MM-y – dd-MM-y GGGGG</greatestDifference>
							<greatestDifference id="y" draft="unconfirmed">dd-MM-y – dd-MM-y GGGGG</greatestDifference>
						</intervalFormatItem>
						<intervalFormatItem id="GyMEd">
							<greatestDifference id="d" draft="unconfirmed">E, dd-MM-y – E, dd-MM-y GGGGG</greatestDifference>
							<greatestDifference id="G" draft="unconfirmed">E, dd-MM-y GGGGG – E, dd-MM-y GGGGG</greatestDifference>
							<greatestDifference id="M" draft="unconfirmed">E, dd-MM-y – E, dd-MM-y GGGGG</greatestDifference>
							<greatestDifference id="y" draft="unconfirmed">E, dd-MM-y – E, dd-MM-y GGGGG</greatestDifference>
						</intervalFormatItem>
						<intervalFormatItem id="GyMMM">
							<greatestDifference id="G" draft="unconfirmed">MMM y G – MMM y G</greatestDifference>
							<greatestDifference id="M" draft="unconfirmed">MMM–MMM y G</greatestDifference>
							<greatestDifference id="y" draft="unconfirmed">MMM y – MMM y G</greatestDifference>
						</intervalFormatItem>
						<intervalFormatItem id="GyMMMd">
							<greatestDifference id="d" draft="unconfirmed">d–d MMM y G</greatestDifference>
							<greatestDifference id="G" draft="unconfirmed">d MMM y G – d MMM y G</greatestDifference>
							<greatestDifference id="M" draft="unconfirmed">d MMM – d MMM y G</greatestDifference>
							<greatestDifference id="y" draft="unconfirmed">d MMM y – d MMM y G</greatestDifference>
						</intervalFormatItem>
						<intervalFormatItem id="GyMMMEd">
							<greatestDifference id="d" draft="unconfirmed">E, d MMM – d MMM y G</greatestDifference>
							<greatestDifference id="G" draft="unconfirmed">E, d MMM y G – E, d MMM y G</greatestDifference>
							<greatestDifference id="M" draft="unconfirmed">E, d MMM – E, d MMM y G</greatestDifference>
							<greatestDifference id="y" draft="unconfirmed">E, d MMM y – E, d MMM y G</greatestDifference>
						</intervalFormatItem>
						<intervalFormatItem id="Md">
							<greatestDifference id="d" draft="unconfirmed">dd-MM – dd-MM</greatestDifference>
							<greatestDifference id="M" draft="unconfirmed">dd-MM – dd-MM</greatestDifference>
						</intervalFormatItem>
						<intervalFormatItem id="MEd">
							<greatestDifference id="d" draft="unconfirmed">E, dd-MM – E, dd-MM</greatestDifference>
							<greatestDifference id="M" draft="unconfirmed">E, dd-MM – E, dd-MM</greatestDifference>
						</intervalFormatItem>
						<intervalFormatItem id="MMMd">
							<greatestDifference id="d" draft="unconfirmed">d–d MMM</greatestDifference>
							<greatestDifference id="M" draft="unconfirmed">d MMM – d MMM</greatestDifference>
						</intervalFormatItem>
						<intervalFormatItem id="MMMEd">
							<greatestDifference id="d" draft="unconfirmed">E, d MMM – E, d MMM</greatestDifference>
							<greatestDifference id="M" draft="unconfirmed">E, d MMM – E, d MMM</greatestDifference>
						</intervalFormatItem>
						<intervalFormatItem id="y">
							<greatestDifference id="y" draft="unconfirmed">y–y G</greatestDifference>
						</intervalFormatItem>
						<intervalFormatItem id="yM">
							<greatestDifference id="M" draft="unconfirmed">MM-y – MM-y GGGGG</greatestDifference>
							<greatestDifference id="y" draft="unconfirmed">MM-y – MM-y GGGGG</greatestDifference>
						</intervalFormatItem>
						<intervalFormatItem id="yMd">
							<greatestDifference id="d" draft="unconfirmed">dd-MM-y – dd-MM-y GGGGG</greatestDifference>
							<greatestDifference id="M" draft="unconfirmed">dd-MM-y – dd-MM-y GGGGG</greatestDifference>
							<greatestDifference id="y" draft="unconfirmed">dd-MM-y – dd-MM-y GGGGG</greatestDifference>
						</intervalFormatItem>
						<intervalFormatItem id="yMEd">
							<greatestDifference id="d" draft="unconfirmed">E, dd-MM-y – E, dd-MM-y GGGGG</greatestDifference>
							<greatestDifference id="M" draft="unconfirmed">E, dd-MM-y – E, dd-MM-y GGGGG</greatestDifference>
							<greatestDifference id="y" draft="unconfirmed">E, dd-MM-y – E, dd-MM-y GGGGG</greatestDifference>
						</intervalFormatItem>
						<intervalFormatItem id="yMMM">
							<greatestDifference id="M" draft="unconfirmed">MMM–MMM y G</greatestDifference>
							<greatestDifference id="y" draft="unconfirmed">MMM y – MMM y G</greatestDifference>
						</intervalFormatItem>
						<intervalFormatItem id="yMMMd">
							<greatestDifference id="d" draft="unconfirmed">d–d MMM y G</greatestDifference>
							<greatestDifference id="M" draft="unconfirmed">d MMM – d MMM y G</greatestDifference>
							<greatestDifference id="y" draft="unconfirmed">d MMM y – d MMM y G</greatestDifference>
						</intervalFormatItem>
						<intervalFormatItem id="yMMMEd">
							<greatestDifference id="d" draft="unconfirmed">E, d MMM – E, d MMM y G</greatestDifference>
							<greatestDifference id="M" draft="unconfirmed">E, d MMM – E, d MMM y G</greatestDifference>
							<greatestDifference id="y" draft="unconfirmed">E, d MMM y – E, d MMM y G</greatestDifference>
						</intervalFormatItem>
						<intervalFormatItem id="yMMMM">
							<greatestDifference id="M" draft="unconfirmed">MMMM–MMMM y G</greatestDifference>
							<greatestDifference id="y" draft="unconfirmed">MMMM y – MMMM y G</greatestDifference>
						</intervalFormatItem>
					</intervalFormats>
				</dateTimeFormats>
			</calendar>
			<calendar type="gregorian">
				<months>
					<monthContext type="format">
						<monthWidth type="abbreviated">
							<month type="1" draft="unconfirmed">Yan</month>
							<month type="2" draft="unconfirmed">Feb</month>
							<month type="3" draft="unconfirmed">Mar</month>
							<month type="4" draft="unconfirmed">Apr</month>
							<month type="5" draft="unconfirmed">Mei</month>
							<month type="6" draft="unconfirmed">Yün</month>
							<month type="7" draft="unconfirmed">Yül</month>
							<month type="8" draft="unconfirmed">Oug</month>
							<month type="9" draft="unconfirmed">Sèp</month>
							<month type="10" draft="unconfirmed">Òkt</month>
							<month type="11" draft="unconfirmed">Nov</month>
							<month type="12" draft="unconfirmed">Des</month>
						</monthWidth>
						<monthWidth type="wide">
							<month type="1">Yanüari</month>
							<month type="2">Febrüari</month>
							<month type="3">Mart</month>
							<month type="4">Aprel</month>
							<month type="5">Mei</month>
							<month type="6">Yüni</month>
							<month type="7">Yüli</month>
							<month type="8">Ougùstùs</month>
							<month type="9">Sèptèmber</month>
							<month type="10">Òktober</month>
							<month type="11">Novèmber</month>
							<month type="12">Desèmber</month>
						</monthWidth>
					</monthContext>
					<monthContext type="stand-alone">
						<monthWidth type="abbreviated">
							<month type="1" draft="unconfirmed">yan</month>
							<month type="2" draft="unconfirmed">feb</month>
							<month type="3" draft="unconfirmed">mar</month>
							<month type="4" draft="unconfirmed">apr</month>
							<month type="5" draft="unconfirmed">mei</month>
							<month type="6" draft="unconfirmed">yün</month>
							<month type="7" draft="unconfirmed">yül</month>
							<month type="8" draft="unconfirmed">oug</month>
							<month type="9" draft="unconfirmed">sèp</month>
							<month type="10" draft="unconfirmed">òkt</month>
							<month type="11" draft="unconfirmed">nov</month>
							<month type="12" draft="unconfirmed">des</month>
						</monthWidth>
					</monthContext>
				</months>
				<days>
					<dayContext type="format">
						<dayWidth type="wide">
							<day type="sun">djadumingu</day>
							<day type="mon">djaluna</day>
							<day type="tue">djamars</day>
							<day type="wed">djarason</day>
							<day type="thu">djaweps</day>
							<day type="fri">djabièrnè</day>
							<day type="sat">djasabra</day>
						</dayWidth>
					</dayContext>
					<dayContext type="stand-alone">
						<dayWidth type="narrow">
							<day type="sun" draft="unconfirmed">dd</day>
							<day type="mon" draft="unconfirmed">dl</day>
							<day type="tue" draft="unconfirmed">dm</day>
							<day type="wed" draft="unconfirmed">dr</day>
							<day type="thu" draft="unconfirmed">dw</day>
							<day type="fri" draft="unconfirmed">db</day>
							<day type="sat" draft="unconfirmed">ds</day>
						</dayWidth>
					</dayContext>
				</days>
				<quarters>
					<quarterContext type="format">
						<quarterWidth type="abbreviated">
							<quarter type="1" draft="unconfirmed">1 kuartal</quarter>
							<quarter type="2" draft="unconfirmed">2 kuartal</quarter>
							<quarter type="3" draft="unconfirmed">3 kuartal</quarter>
							<quarter type="4" draft="unconfirmed">4 kuartal</quarter>
						</quarterWidth>
						<quarterWidth type="wide">
							<quarter type="1" draft="unconfirmed">di promé kuartal</quarter>
							<quarter type="2" draft="unconfirmed">di dos kuartal</quarter>
							<quarter type="3" draft="unconfirmed">di tres kuartal</quarter>
							<quarter type="4" draft="unconfirmed">di kuanter kuartal</quarter>
						</quarterWidth>
					</quarterContext>
					<quarterContext type="stand-alone">
						<quarterWidth type="abbreviated">
							<quarter type="1" draft="unconfirmed">1 kuartal</quarter>
							<quarter type="2" draft="unconfirmed">2 kuartal</quarter>
							<quarter type="3" draft="unconfirmed">3 kuartal</quarter>
							<quarter type="4" draft="unconfirmed">4 kuartal</quarter>
						</quarterWidth>
						<quarterWidth type="wide">
							<quarter type="1" draft="unconfirmed">di promé kuartal</quarter>
							<quarter type="2" draft="unconfirmed">di dos kuartal</quarter>
							<quarter type="3" draft="unconfirmed">di tres kuartal</quarter>
							<quarter type="4" draft="unconfirmed">di kuanter kuartal</quarter>
						</quarterWidth>
					</quarterContext>
				</quarters>
				<eras>
					<eraNames>
						<era type="0" draft="unconfirmed">Promé ku Kristu</era>
						<era type="0" alt="variant" draft="unconfirmed">Promé ku Era Komun</era>
						<era type="1" draft="unconfirmed">Despues di Kristu</era>
						<era type="1" alt="variant" draft="unconfirmed">Era Komun</era>
					</eraNames>
					<eraAbbr>
						<era type="0" draft="unconfirmed">P.K</era>
						<era type="0" alt="variant" draft="unconfirmed">P.E.K</era>
						<era type="1" draft="unconfirmed">D.K</era>
						<era type="1" alt="variant" draft="unconfirmed">E.K</era>
					</eraAbbr>
				</eras>
				<dateFormats>
					<dateFormatLength type="full">
						<dateFormat>
							<pattern draft="unconfirmed">EEEE, d MMMM y</pattern>
						</dateFormat>
					</dateFormatLength>
					<dateFormatLength type="long">
						<dateFormat>
							<pattern draft="unconfirmed">d MMMM y</pattern>
						</dateFormat>
					</dateFormatLength>
					<dateFormatLength type="medium">
						<dateFormat>
							<pattern draft="unconfirmed">d MMM y</pattern>
						</dateFormat>
					</dateFormatLength>
					<dateFormatLength type="short">
						<dateFormat>
							<pattern draft="unconfirmed">dd-MM-y</pattern>
						</dateFormat>
					</dateFormatLength>
				</dateFormats>
				<timeFormats>
					<timeFormatLength type="full">
						<timeFormat>
							<pattern draft="unconfirmed">HH:mm:ss zzzz</pattern>
						</timeFormat>
					</timeFormatLength>
					<timeFormatLength type="long">
						<timeFormat>
							<pattern draft="unconfirmed">HH:mm:ss z</pattern>
						</timeFormat>
					</timeFormatLength>
					<timeFormatLength type="medium">
						<timeFormat>
							<pattern draft="unconfirmed">HH:mm:ss</pattern>
						</timeFormat>
					</timeFormatLength>
					<timeFormatLength type="short">
						<timeFormat>
							<pattern draft="unconfirmed">HH:mm</pattern>
						</timeFormat>
					</timeFormatLength>
				</timeFormats>
				<dateTimeFormats>
					<dateTimeFormatLength type="full">
						<dateTimeFormat>
							<pattern draft="unconfirmed">{1} {0}</pattern>
						</dateTimeFormat>
					</dateTimeFormatLength>
					<dateTimeFormatLength type="long">
						<dateTimeFormat>
							<pattern draft="unconfirmed">{1} {0}</pattern>
						</dateTimeFormat>
					</dateTimeFormatLength>
					<dateTimeFormatLength type="medium">
						<dateTimeFormat>
							<pattern draft="unconfirmed">{1} {0}</pattern>
						</dateTimeFormat>
					</dateTimeFormatLength>
					<dateTimeFormatLength type="short">
						<dateTimeFormat>
							<pattern draft="unconfirmed">{1} {0}</pattern>
						</dateTimeFormat>
					</dateTimeFormatLength>
					<availableFormats>
						<dateFormatItem id="Ed" draft="unconfirmed">E, d</dateFormatItem>
						<dateFormatItem id="Gy" draft="unconfirmed">y G</dateFormatItem>
						<dateFormatItem id="GyMd" draft="unconfirmed">dd-MM-y GGGGG</dateFormatItem>
						<dateFormatItem id="GyMMM" draft="unconfirmed">MMM y G</dateFormatItem>
						<dateFormatItem id="GyMMMd" draft="unconfirmed">d MMM y G</dateFormatItem>
						<dateFormatItem id="GyMMMEd" draft="unconfirmed">E, d MMM y G</dateFormatItem>
						<dateFormatItem id="Md" draft="unconfirmed">dd-MM</dateFormatItem>
						<dateFormatItem id="MEd" draft="unconfirmed">E, dd-MM</dateFormatItem>
						<dateFormatItem id="MMMd" draft="unconfirmed">d MMM</dateFormatItem>
						<dateFormatItem id="MMMEd" draft="unconfirmed">E, d MMM</dateFormatItem>
						<dateFormatItem id="MMMMd" draft="unconfirmed">d MMMM</dateFormatItem>
						<dateFormatItem id="MMMMW" count="one" draft="unconfirmed">'siman' W 'di' MMMM</dateFormatItem>
						<dateFormatItem id="MMMMW" count="other" draft="unconfirmed">'siman' W 'di' MMMM</dateFormatItem>
						<dateFormatItem id="yM" draft="unconfirmed">MM-y</dateFormatItem>
						<dateFormatItem id="yMd" draft="unconfirmed">dd-MM-y</dateFormatItem>
						<dateFormatItem id="yMEd" draft="unconfirmed">E, dd-MM-y</dateFormatItem>
						<dateFormatItem id="yMMM" draft="unconfirmed">MMM y</dateFormatItem>
						<dateFormatItem id="yMMMd" draft="unconfirmed">d MMM y</dateFormatItem>
						<dateFormatItem id="yMMMEd" draft="unconfirmed">E, d MMM y</dateFormatItem>
						<dateFormatItem id="yMMMM" draft="unconfirmed">MMMM y</dateFormatItem>
						<dateFormatItem id="yQQQ" draft="unconfirmed">QQQ y</dateFormatItem>
						<dateFormatItem id="yQQQQ" draft="unconfirmed">QQQQ y</dateFormatItem>
						<dateFormatItem id="yw" count="one" draft="unconfirmed">'siman' w 'di' Y</dateFormatItem>
						<dateFormatItem id="yw" count="other" draft="unconfirmed">'siman' w 'di' Y</dateFormatItem>
					</availableFormats>
					<intervalFormats>
						<intervalFormatItem id="Gy">
							<greatestDifference id="G" draft="unconfirmed">y G – y G</greatestDifference>
							<greatestDifference id="y" draft="unconfirmed">y–y G</greatestDifference>
						</intervalFormatItem>
						<intervalFormatItem id="GyM">
							<greatestDifference id="G" draft="unconfirmed">MM-y GGGGG – MM-y GGGGG</greatestDifference>
							<greatestDifference id="M" draft="unconfirmed">MM-y – MM-y GGGGG</greatestDifference>
							<greatestDifference id="y" draft="unconfirmed">MM-y – MM-y GGGGG</greatestDifference>
						</intervalFormatItem>
						<intervalFormatItem id="GyMd">
							<greatestDifference id="d" draft="unconfirmed">dd-MM-y – dd-MM-y GGGGG</greatestDifference>
							<greatestDifference id="G" draft="unconfirmed">dd-MM-y GGGGG – dd-MM-y GGGGG</greatestDifference>
							<greatestDifference id="M" draft="unconfirmed">dd-MM-y – dd-MM-y GGGGG</greatestDifference>
							<greatestDifference id="y" draft="unconfirmed">dd-MM-y – dd-MM-y GGGGG</greatestDifference>
						</intervalFormatItem>
						<intervalFormatItem id="GyMEd">
							<greatestDifference id="d" draft="unconfirmed">E, dd-MM-y – E, dd-MM-y GGGGG</greatestDifference>
							<greatestDifference id="G" draft="unconfirmed">E, dd-MM-y GGGGG – E, dd-MM-y GGGGG</greatestDifference>
							<greatestDifference id="M" draft="unconfirmed">E, dd-MM-y – E, dd-MM-y GGGGG</greatestDifference>
							<greatestDifference id="y" draft="unconfirmed">E, dd-MM-y – E, dd-MM-y GGGGG</greatestDifference>
						</intervalFormatItem>
						<intervalFormatItem id="GyMMM">
							<greatestDifference id="G" draft="unconfirmed">MMM y G – MMM y G</greatestDifference>
							<greatestDifference id="M" draft="unconfirmed">MMM–MMM y G</greatestDifference>
							<greatestDifference id="y" draft="unconfirmed">MMM y – MMM y G</greatestDifference>
						</intervalFormatItem>
						<intervalFormatItem id="GyMMMd">
							<greatestDifference id="d" draft="unconfirmed">d–d MMM y G</greatestDifference>
							<greatestDifference id="G" draft="unconfirmed">d y MMM y G – d MMM y G</greatestDifference>
							<greatestDifference id="M" draft="unconfirmed">d MMM – d MMM y G</greatestDifference>
							<greatestDifference id="y" draft="unconfirmed">d MMM y – d MMM y G</greatestDifference>
						</intervalFormatItem>
						<intervalFormatItem id="GyMMMEd">
							<greatestDifference id="d" draft="unconfirmed">E, d MMM – E, d MMM y G</greatestDifference>
							<greatestDifference id="G" draft="unconfirmed">E, d MMM y – E, d MMM y G</greatestDifference>
							<greatestDifference id="M" draft="unconfirmed">E, d MMM – E, d MMM y G</greatestDifference>
							<greatestDifference id="y" draft="unconfirmed">E, d MMM y – E, d MMM y G</greatestDifference>
						</intervalFormatItem>
						<intervalFormatItem id="Md">
							<greatestDifference id="d" draft="unconfirmed">dd-MM – dd-MM</greatestDifference>
							<greatestDifference id="M" draft="unconfirmed">dd-MM – dd-MM</greatestDifference>
						</intervalFormatItem>
						<intervalFormatItem id="MEd">
							<greatestDifference id="d" draft="unconfirmed">E, dd-MM – E, dd-MM</greatestDifference>
							<greatestDifference id="M" draft="unconfirmed">E, dd-MM – E, dd-MM</greatestDifference>
						</intervalFormatItem>
						<intervalFormatItem id="MMMd">
							<greatestDifference id="d" draft="unconfirmed">d–d MMM</greatestDifference>
							<greatestDifference id="M" draft="unconfirmed">d MMM – d MMM</greatestDifference>
						</intervalFormatItem>
						<intervalFormatItem id="MMMEd">
							<greatestDifference id="d" draft="unconfirmed">E, d MMM – E, d MMM</greatestDifference>
							<greatestDifference id="M" draft="unconfirmed">E, d MMM – E, d MMM</greatestDifference>
						</intervalFormatItem>
						<intervalFormatItem id="yM">
							<greatestDifference id="M" draft="unconfirmed">MM-y – MM-y</greatestDifference>
							<greatestDifference id="y" draft="unconfirmed">MM-y – MM-y</greatestDifference>
						</intervalFormatItem>
						<intervalFormatItem id="yMd">
							<greatestDifference id="d" draft="unconfirmed">dd-MM-y – dd-MM-y</greatestDifference>
							<greatestDifference id="M" draft="unconfirmed">dd-MM-y – dd-MM-y</greatestDifference>
							<greatestDifference id="y" draft="unconfirmed">dd-MM-y – dd-MM-y</greatestDifference>
						</intervalFormatItem>
						<intervalFormatItem id="yMEd">
							<greatestDifference id="d" draft="unconfirmed">E, dd-MM-y – E, dd-MM-y</greatestDifference>
							<greatestDifference id="M" draft="unconfirmed">E, dd-MM-y – E, dd-MM-y</greatestDifference>
							<greatestDifference id="y" draft="unconfirmed">E, dd-MM-y – E, dd-MM-y</greatestDifference>
						</intervalFormatItem>
						<intervalFormatItem id="yMMM">
							<greatestDifference id="M" draft="unconfirmed">MMM–MMM y</greatestDifference>
							<greatestDifference id="y" draft="unconfirmed">MMM y – MMM y</greatestDifference>
						</intervalFormatItem>
						<intervalFormatItem id="yMMMd">
							<greatestDifference id="d" draft="unconfirmed">d–d MMM y</greatestDifference>
							<greatestDifference id="M" draft="unconfirmed">d MMM – d MMM y</greatestDifference>
							<greatestDifference id="y" draft="unconfirmed">d MMM y – d MMM y</greatestDifference>
						</intervalFormatItem>
						<intervalFormatItem id="yMMMEd">
							<greatestDifference id="d" draft="unconfirmed">E, d MMM – E, d MMM y</greatestDifference>
							<greatestDifference id="M" draft="unconfirmed">E, d MMM – E, d MMM y</greatestDifference>
							<greatestDifference id="y" draft="unconfirmed">E, d MMM y – E, d MMM y</greatestDifference>
						</intervalFormatItem>
						<intervalFormatItem id="yMMMM">
							<greatestDifference id="M" draft="unconfirmed">MMMM–MMMM y</greatestDifference>
							<greatestDifference id="y" draft="unconfirmed">MMMM y – MMMM y</greatestDifference>
						</intervalFormatItem>
					</intervalFormats>
				</dateTimeFormats>
			</calendar>
		</calendars>
		<fields>
			<field type="year">
				<displayName draft="unconfirmed">aña</displayName>
				<relative type="-1" draft="unconfirmed">aña pasá</relative>
				<relative type="0" draft="unconfirmed">e aña akí</relative>
				<relative type="1" draft="unconfirmed">otro aña</relative>
			</field>
			<field type="month">
				<displayName draft="unconfirmed">luna</displayName>
				<relative type="-1" draft="unconfirmed">luna pasá</relative>
				<relative type="0" draft="unconfirmed">e luna akí</relative>
				<relative type="1" draft="unconfirmed">otro luna</relative>
			</field>
			<field type="week">
				<displayName draft="unconfirmed">siman</displayName>
				<relative type="-1" draft="unconfirmed">siman pasá</relative>
				<relative type="0" draft="unconfirmed">e siman akí</relative>
				<relative type="1" draft="unconfirmed">otro siman</relative>
				<relativePeriod draft="unconfirmed">e siman di {0}</relativePeriod>
			</field>
			<field type="day">
				<displayName draft="unconfirmed">dia</displayName>
				<relative type="-1" draft="unconfirmed">ayera</relative>
				<relative type="0" draft="unconfirmed">awe</relative>
				<relative type="1" draft="unconfirmed">mañan</relative>
			</field>
			<field type="weekday">
				<displayName draft="unconfirmed">dia di siman</displayName>
			</field>
			<field type="dayperiod">
				<displayName draft="unconfirmed">periodo di dia</displayName>
			</field>
			<field type="hour">
				<displayName draft="unconfirmed">ora</displayName>
			</field>
			<field type="minute">
				<displayName draft="unconfirmed">minüt</displayName>
			</field>
			<field type="second">
				<displayName draft="unconfirmed">sekònde</displayName>
			</field>
			<field type="zone">
				<displayName draft="unconfirmed">zona di ora</displayName>
			</field>
		</fields>
		<timeZoneNames>
			<regionFormat draft="unconfirmed">ora di {0}</regionFormat>
			<zone type="Etc/Unknown">
				<exemplarCity draft="unconfirmed">Deskonosí</exemplarCity>
			</zone>
			<zone type="America/St_Johns">
				<exemplarCity draft="unconfirmed">Sint John’s</exemplarCity>
			</zone>
			<zone type="Atlantic/Cape_Verde">
				<exemplarCity draft="unconfirmed">Kabo Verde</exemplarCity>
			</zone>
			<zone type="America/Curacao">
				<exemplarCity draft="unconfirmed">Kòrsou</exemplarCity>
			</zone>
			<zone type="America/Santo_Domingo">
				<exemplarCity draft="unconfirmed">Repúblka Dominicana</exemplarCity>
			</zone>
			<zone type="Europe/London">
				<exemplarCity draft="unconfirmed">Lònden</exemplarCity>
			</zone>
			<zone type="Europe/Athens">
				<exemplarCity draft="unconfirmed">Aténas</exemplarCity>
			</zone>
			<zone type="Asia/Jerusalem">
				<exemplarCity draft="unconfirmed">Herúsalèm</exemplarCity>
			</zone>
			<zone type="Europe/Rome">
				<exemplarCity draft="unconfirmed">Roma</exemplarCity>
			</zone>
			<zone type="America/St_Kitts">
				<exemplarCity draft="unconfirmed">Sint Kitts</exemplarCity>
			</zone>
			<zone type="America/St_Lucia">
				<exemplarCity draft="unconfirmed">Sint Lucia</exemplarCity>
			</zone>
			<zone type="America/Panama">
				<exemplarCity draft="unconfirmed">Panamá</exemplarCity>
			</zone>
			<zone type="Atlantic/Azores">
				<exemplarCity draft="unconfirmed">Azóres</exemplarCity>
			</zone>
			<zone type="America/St_Vincent">
				<exemplarCity draft="unconfirmed">Sint Vincent</exemplarCity>
			</zone>
			<zone type="America/St_Thomas">
				<exemplarCity draft="unconfirmed">Sint Thomas</exemplarCity>
			</zone>
			<metazone type="Africa_Central">
				<long>
					<standard draft="unconfirmed">Ora di Áfrika Sentral</standard>
				</long>
			</metazone>
			<metazone type="Africa_Eastern">
				<long>
					<standard draft="unconfirmed">Ora di Ost Áfrika</standard>
				</long>
			</metazone>
			<metazone type="Azores">
				<long>
					<generic draft="unconfirmed">Ora di Azóres</generic>
					<standard draft="unconfirmed">Ora Normal di Azóres</standard>
					<daylight draft="unconfirmed">Ora di Azóres Temporada di Zomer</daylight>
				</long>
			</metazone>
			<metazone type="Europe_Central">
				<long>
					<generic draft="unconfirmed">Ora di Europa Sentral</generic>
					<standard draft="unconfirmed">Ora Normal di Europa Sentral</standard>
					<daylight draft="unconfirmed">Ora di Europa Sentral Temporada di Zomer</daylight>
				</long>
			</metazone>
			<metazone type="Europe_Eastern">
				<long>
					<generic draft="unconfirmed">Ora di Ost Europa</generic>
					<standard draft="unconfirmed">Ora Normal di Ost Europa</standard>
					<daylight draft="unconfirmed">Ora di Ost Europa Temporada di Zomer</daylight>
				</long>
			</metazone>
			<metazone type="Europe_Western">
				<long>
					<generic draft="unconfirmed">Ora di Wèst Europa</generic>
					<standard draft="unconfirmed">Ora Normal di Wèst Europa</standard>
					<daylight draft="unconfirmed">Ora di Wèst Europa Temporada di Zomer</daylight>
				</long>
			</metazone>
			<metazone type="GMT">
				<long>
					<standard draft="unconfirmed">Greenwich Mean Time</standard>
				</long>
			</metazone>
		</timeZoneNames>
	</dates>
	<numbers>
		<decimalFormats numberSystem="latn">
			<decimalFormatLength type="long">
				<decimalFormat>
					<pattern type="1000" count="one" draft="unconfirmed">0 mil</pattern>
					<pattern type="1000" count="other" draft="unconfirmed">0 mil</pattern>
					<pattern type="10000" count="one" draft="unconfirmed">00 mil</pattern>
					<pattern type="10000" count="other" draft="unconfirmed">00 mil</pattern>
					<pattern type="100000" count="one" draft="unconfirmed">000 mil</pattern>
					<pattern type="100000" count="other" draft="unconfirmed">000 mil</pattern>
					<pattern type="1000000" count="one" draft="unconfirmed">0 mion</pattern>
					<pattern type="1000000" count="other" draft="unconfirmed">0 mion</pattern>
					<pattern type="10000000" count="one" draft="unconfirmed">00 mion</pattern>
					<pattern type="10000000" count="other" draft="unconfirmed">00 mion</pattern>
					<pattern type="100000000" count="one" draft="unconfirmed">000 mion</pattern>
					<pattern type="100000000" count="other" draft="unconfirmed">000 mion</pattern>
					<pattern type="1000000000" count="one" draft="unconfirmed">0 bion</pattern>
					<pattern type="1000000000" count="other" draft="unconfirmed">0 bion</pattern>
					<pattern type="10000000000" count="one" draft="unconfirmed">00 bion</pattern>
					<pattern type="10000000000" count="other" draft="unconfirmed">00 bion</pattern>
					<pattern type="100000000000" count="one" draft="unconfirmed">000 bion</pattern>
					<pattern type="100000000000" count="other" draft="unconfirmed">000 bion</pattern>
					<pattern type="1000000000000" count="one" draft="unconfirmed">0 trion</pattern>
					<pattern type="1000000000000" count="other" draft="unconfirmed">0 trion</pattern>
					<pattern type="10000000000000" count="one" draft="unconfirmed">00 trion</pattern>
					<pattern type="10000000000000" count="other" draft="unconfirmed">00 trion</pattern>
					<pattern type="100000000000000" count="one" draft="unconfirmed">000 trion</pattern>
					<pattern type="100000000000000" count="other" draft="unconfirmed">000 trion</pattern>
				</decimalFormat>
			</decimalFormatLength>
			<decimalFormatLength type="short">
				<decimalFormat>
					<pattern type="1000" count="one" draft="unconfirmed">0mil</pattern>
					<pattern type="1000" count="other" draft="unconfirmed">0mil</pattern>
					<pattern type="10000" count="one" draft="unconfirmed">00mil</pattern>
					<pattern type="10000" count="other" draft="unconfirmed">00mil</pattern>
					<pattern type="100000" count="one" draft="unconfirmed">000mil</pattern>
					<pattern type="100000" count="other" draft="unconfirmed">000mil</pattern>
					<pattern type="1000000" count="one" draft="unconfirmed">0mion</pattern>
					<pattern type="1000000" count="other" draft="unconfirmed">0mion</pattern>
					<pattern type="10000000" count="one" draft="unconfirmed">00mion</pattern>
					<pattern type="10000000" count="other" draft="unconfirmed">00mion</pattern>
					<pattern type="100000000" count="one" draft="unconfirmed">000mion</pattern>
					<pattern type="100000000" count="other" draft="unconfirmed">000mion</pattern>
					<pattern type="1000000000" count="one" draft="unconfirmed">0bion</pattern>
					<pattern type="1000000000" count="other" draft="unconfirmed">0bion</pattern>
					<pattern type="10000000000" count="one" draft="unconfirmed">00bion</pattern>
					<pattern type="10000000000" count="other" draft="unconfirmed">00bion</pattern>
					<pattern type="100000000000" count="one" draft="unconfirmed">000bion</pattern>
					<pattern type="100000000000" count="other" draft="unconfirmed">000bion</pattern>
					<pattern type="1000000000000" count="one" draft="unconfirmed">0trion</pattern>
					<pattern type="1000000000000" count="other" draft="unconfirmed">0trion</pattern>
					<pattern type="10000000000000" count="one" draft="unconfirmed">00trion</pattern>
					<pattern type="10000000000000" count="other" draft="unconfirmed">00trion</pattern>
					<pattern type="100000000000000" count="one" draft="unconfirmed">000trion</pattern>
					<pattern type="100000000000000" count="other" draft="unconfirmed">000trion</pattern>
				</decimalFormat>
			</decimalFormatLength>
		</decimalFormats>
		<currencyFormats numberSystem="latn">
			<currencyFormatLength type="short">
				<currencyFormat type="standard">
					<pattern type="1000" count="one" draft="unconfirmed">¤0mil</pattern>
					<pattern type="1000" count="other" draft="unconfirmed">¤0mil</pattern>
					<pattern type="10000" count="one" draft="unconfirmed">¤00mil</pattern>
					<pattern type="10000" count="other" draft="unconfirmed">¤00mil</pattern>
					<pattern type="100000" count="one" draft="unconfirmed">¤000mil</pattern>
					<pattern type="100000" count="other" draft="unconfirmed">¤000mil</pattern>
					<pattern type="1000000" count="one" draft="unconfirmed">¤0mion</pattern>
					<pattern type="1000000" count="other" draft="unconfirmed">¤0mion</pattern>
					<pattern type="10000000" count="one" draft="unconfirmed">¤00mion</pattern>
					<pattern type="10000000" count="other" draft="unconfirmed">¤00mion</pattern>
					<pattern type="100000000" count="one" draft="unconfirmed">¤000mion</pattern>
					<pattern type="100000000" count="other" draft="unconfirmed">¤000mion</pattern>
					<pattern type="1000000000" count="one" draft="unconfirmed">¤0bion</pattern>
					<pattern type="1000000000" count="other" draft="unconfirmed">¤0bion</pattern>
					<pattern type="10000000000" count="one" draft="unconfirmed">¤00bion</pattern>
					<pattern type="10000000000" count="other" draft="unconfirmed">¤00bion</pattern>
					<pattern type="100000000000" count="one" draft="unconfirmed">¤000bion</pattern>
					<pattern type="100000000000" count="other" draft="unconfirmed">¤000bion</pattern>
					<pattern type="1000000000000" count="one" draft="unconfirmed">¤0trion</pattern>
					<pattern type="1000000000000" count="other" draft="unconfirmed">¤0trion</pattern>
					<pattern type="10000000000000" count="one" draft="unconfirmed">¤00trion</pattern>
					<pattern type="10000000000000" count="other" draft="unconfirmed">¤00trion</pattern>
					<pattern type="100000000000000" count="one" draft="unconfirmed">¤000trion</pattern>
					<pattern type="100000000000000" count="other" draft="unconfirmed">¤000trion</pattern>
				</currencyFormat>
			</currencyFormatLength>
		</currencyFormats>
		<currencies>
			<currency type="ANG">
				<displayName draft="unconfirmed">Florin</displayName>
			</currency>
			<currency type="AWG">
				<displayName draft="unconfirmed">Florin di Aruba</displayName>
			</currency>
			<currency type="BMD">
				<displayName draft="unconfirmed">Dòler di Bermuda</displayName>
			</currency>
			<currency type="BZD">
				<displayName draft="unconfirmed">Dòler di Belize</displayName>
			</currency>
			<currency type="CAD">
				<displayName draft="unconfirmed">Dòler kanades</displayName>
			</currency>
			<currency type="USD">
				<displayName draft="unconfirmed">Dòler merikano</displayName>
			</currency>
		</currencies>
		<minimalPairs>
			<pluralMinimalPairs count="one" draft="unconfirmed">{0} dia</pluralMinimalPairs>
			<pluralMinimalPairs count="other" draft="unconfirmed">{0} dianan</pluralMinimalPairs>
			<ordinalMinimalPairs ordinal="other" draft="unconfirmed">di {0}</ordinalMinimalPairs>
		</minimalPairs>
	</numbers>
	<units>
		<unitLength type="long">
			<compoundUnit type="per">
				<compoundUnitPattern draft="unconfirmed">{0} pa {1}</compoundUnitPattern>
			</compoundUnit>
			<compoundUnit type="times">
				<compoundUnitPattern draft="unconfirmed">{0}-{1}</compoundUnitPattern>
			</compoundUnit>
			<coordinateUnit>
				<coordinateUnitPattern type="east" draft="unconfirmed">{0} ost</coordinateUnitPattern>
				<coordinateUnitPattern type="north" draft="unconfirmed">{0} nort</coordinateUnitPattern>
				<coordinateUnitPattern type="south" draft="unconfirmed">{0} suit</coordinateUnitPattern>
				<coordinateUnitPattern type="west" draft="unconfirmed">{0} wèst</coordinateUnitPattern>
			</coordinateUnit>
		</unitLength>
		<unitLength type="short">
			<coordinateUnit>
				<displayName draft="unconfirmed">direkshon</displayName>
				<coordinateUnitPattern type="east" draft="unconfirmed">{0} ost</coordinateUnitPattern>
				<coordinateUnitPattern type="north" draft="unconfirmed">{0} nort</coordinateUnitPattern>
				<coordinateUnitPattern type="south" draft="unconfirmed">{0} suit</coordinateUnitPattern>
				<coordinateUnitPattern type="west" draft="unconfirmed">{0} wèst</coordinateUnitPattern>
			</coordinateUnit>
		</unitLength>
		<unitLength type="narrow">
			<coordinateUnit>
				<coordinateUnitPattern type="east" draft="unconfirmed">{0} ost</coordinateUnitPattern>
				<coordinateUnitPattern type="north" draft="unconfirmed">{0} nort</coordinateUnitPattern>
				<coordinateUnitPattern type="south" draft="unconfirmed">{0} suit</coordinateUnitPattern>
				<coordinateUnitPattern type="west" draft="unconfirmed">{0} wèst</coordinateUnitPattern>
			</coordinateUnit>
		</unitLength>
	</units>
	<listPatterns>
		<listPattern>
			<listPatternPart type="end" draft="unconfirmed">{0}, i {1}</listPatternPart>
			<listPatternPart type="2" draft="unconfirmed">{0} i {1}</listPatternPart>
		</listPattern>
		<listPattern type="or">
			<listPatternPart type="end" draft="unconfirmed">{0} òf {1}</listPatternPart>
			<listPatternPart type="2" draft="unconfirmed">{0} òf {1}</listPatternPart>
		</listPattern>
		<listPattern type="standard-narrow">
			<listPatternPart type="end" draft="unconfirmed">{0}, i {1}</listPatternPart>
			<listPatternPart type="2" draft="unconfirmed">{0} &amp; {1}</listPatternPart>
		</listPattern>
		<listPattern type="standard-short">
			<listPatternPart type="end" draft="unconfirmed">{0}, i {1}</listPatternPart>
			<listPatternPart type="2" draft="unconfirmed">{0} i {1}</listPatternPart>
		</listPattern>
		<listPattern type="unit-short">
			<listPatternPart type="2" draft="unconfirmed">{0} i {1}</listPatternPart>
		</listPattern>
	</listPatterns>
	<characterLabels>
		<characterLabelPattern type="all" draft="unconfirmed">{0} — tur</characterLabelPattern>
		<characterLabelPattern type="historic" draft="unconfirmed">{0} — históriko</characterLabelPattern>
		<characterLabelPattern type="other" draft="unconfirmed">{0} — otro</characterLabelPattern>
		<characterLabel type="animal" draft="unconfirmed">bestia</characterLabel>
		<characterLabel type="animals_nature" draft="unconfirmed">bestia òf naturalesa</characterLabel>
		<characterLabel type="arrows" draft="unconfirmed">flecha</characterLabel>
		<characterLabel type="body" draft="unconfirmed">kurpa</characterLabel>
		<characterLabel type="building" draft="unconfirmed">edifisio</characterLabel>
		<characterLabel type="bullets_stars" draft="unconfirmed">bullet òf strea</characterLabel>
		<characterLabel type="female" draft="unconfirmed">muhé</characterLabel>
		<characterLabel type="flag" draft="unconfirmed">bandera</characterLabel>
		<characterLabel type="flags" draft="unconfirmed">bandera</characterLabel>
		<characterLabel type="food_drink" draft="unconfirmed">kuminda òf bebida</characterLabel>
		<characterLabel type="heart" draft="unconfirmed">kurason</characterLabel>
		<characterLabel type="male" draft="unconfirmed">hòmber</characterLabel>
		<characterLabel type="musical_symbols" draft="unconfirmed">símbolo musikal</characterLabel>
		<characterLabel type="nature" draft="unconfirmed">naturalesa</characterLabel>
		<characterLabel type="numbers" draft="unconfirmed">number</characterLabel>
		<characterLabel type="objects" draft="unconfirmed">opheto</characterLabel>
		<characterLabel type="other" draft="unconfirmed">otro</characterLabel>
		<characterLabel type="person" draft="unconfirmed">persona</characterLabel>
		<characterLabel type="place" draft="unconfirmed">lugá</characterLabel>
		<characterLabel type="plant" draft="unconfirmed">planchi</characterLabel>
		<characterLabel type="punctuation" draft="unconfirmed">puntuashon</characterLabel>
		<characterLabel type="sign_standard_symbols" draft="unconfirmed">señal òf símbolo</characterLabel>
		<characterLabel type="smileys_people" draft="unconfirmed">smiley òf persona</characterLabel>
		<characterLabel type="sport" draft="unconfirmed">deporte</characterLabel>
		<characterLabel type="symbols" draft="unconfirmed">símbolo</characterLabel>
		<characterLabel type="travel" draft="unconfirmed">biaha</characterLabel>
		<characterLabel type="travel_places" draft="unconfirmed">biaha òf lugá</characterLabel>
		<characterLabel type="weather" draft="unconfirmed">wer</characterLabel>
	</characterLabels>
	<personNames>
		<nameOrderLocales order="givenFirst" draft="unconfirmed">und pap</nameOrderLocales>
		<initialPattern type="initialSequence" draft="unconfirmed">{0}{1}</initialPattern>
		<personName order="givenFirst" length="long" usage="referring" formality="formal">
			<namePattern draft="unconfirmed">{title} {given} {given2} {surname} {surname2}</namePattern>
		</personName>
		<personName order="givenFirst" length="long" usage="referring" formality="informal">
			<namePattern draft="unconfirmed">{given} {surname}</namePattern>
		</personName>
		<personName order="givenFirst" length="long" usage="addressing" formality="formal">
			<namePattern draft="unconfirmed">{title} {given} {surname}</namePattern>
		</personName>
		<personName order="givenFirst" length="long" usage="addressing" formality="informal">
			<namePattern draft="unconfirmed">{given} {surname}</namePattern>
		</personName>
		<personName order="givenFirst" length="long" usage="monogram" formality="informal">
			<namePattern draft="unconfirmed">{given-informal-monogram-allCaps}{surname-monogram-allCaps}</namePattern>
		</personName>
		<personName order="givenFirst" length="medium" usage="referring" formality="informal">
			<namePattern draft="unconfirmed">{given} {surname}</namePattern>
		</personName>
		<personName order="givenFirst" length="medium" usage="addressing" formality="formal">
			<namePattern draft="unconfirmed">{title} {surname}</namePattern>
		</personName>
		<personName order="givenFirst" length="medium" usage="addressing" formality="informal">
			<namePattern draft="unconfirmed">{given-informal}</namePattern>
		</personName>
		<personName order="givenFirst" length="medium" usage="monogram" formality="formal">
			<namePattern draft="unconfirmed">{given-monogram-allCaps}{surname-monogram-allCaps}</namePattern>
		</personName>
		<personName order="givenFirst" length="medium" usage="monogram" formality="informal">
			<namePattern draft="unconfirmed">{given-monogram-allCaps}{surname-monogram-allCaps}</namePattern>
		</personName>
		<personName order="givenFirst" length="short" usage="referring" formality="formal">
			<namePattern draft="unconfirmed">{given-initial}{given2-initial} {surname}</namePattern>
		</personName>
		<personName order="givenFirst" length="short" usage="referring" formality="informal">
			<namePattern draft="unconfirmed">{given-informal} {surname-initial}</namePattern>
		</personName>
		<personName order="givenFirst" length="short" usage="addressing" formality="formal">
			<namePattern draft="unconfirmed">{title} {surname}</namePattern>
		</personName>
		<personName order="givenFirst" length="short" usage="addressing" formality="informal">
			<namePattern draft="unconfirmed">{given-informal}</namePattern>
		</personName>
		<personName order="givenFirst" length="short" usage="monogram" formality="formal">
			<namePattern draft="unconfirmed">{surname-monogram-allCaps}</namePattern>
		</personName>
		<personName order="givenFirst" length="short" usage="monogram" formality="informal">
			<namePattern draft="unconfirmed">{given-informal-monogram-allCaps}</namePattern>
		</personName>
		<personName order="surnameFirst" length="long" usage="referring" formality="formal">
			<namePattern draft="unconfirmed">{title} {surname} {surname2} {given} {given2}</namePattern>
		</personName>
		<personName order="surnameFirst" length="long" usage="referring" formality="informal">
			<namePattern draft="unconfirmed">{surname} {given-informal}</namePattern>
		</personName>
		<personName order="surnameFirst" length="long" usage="addressing" formality="formal">
			<namePattern draft="unconfirmed">{title} {surname}</namePattern>
		</personName>
		<personName order="surnameFirst" length="long" usage="addressing" formality="informal">
			<namePattern draft="unconfirmed">{given-informal}</namePattern>
		</personName>
		<personName order="surnameFirst" length="long" usage="monogram" formality="informal">
			<namePattern draft="unconfirmed">{surname-monogram-allCaps}{given-informal-monogram-allCaps}</namePattern>
		</personName>
		<personName order="surnameFirst" length="medium" usage="referring" formality="formal">
			<namePattern draft="unconfirmed">{surname} {given} {given2-initial} {generation}, {credentials}</namePattern>
		</personName>
		<personName order="surnameFirst" length="medium" usage="referring" formality="informal">
			<namePattern draft="unconfirmed">{surname} {given-informal}</namePattern>
		</personName>
		<personName order="surnameFirst" length="medium" usage="addressing" formality="formal">
			<namePattern draft="unconfirmed">{title} {surname} {given}</namePattern>
		</personName>
		<personName order="surnameFirst" length="medium" usage="addressing" formality="informal">
			<namePattern draft="unconfirmed">{given-informal}</namePattern>
		</personName>
		<personName order="surnameFirst" length="medium" usage="monogram" formality="formal">
			<namePattern draft="unconfirmed">{surname-monogram-allCaps}</namePattern>
		</personName>
		<personName order="surnameFirst" length="medium" usage="monogram" formality="informal">
			<namePattern draft="unconfirmed">{given-informal-monogram-allCaps}</namePattern>
		</personName>
		<personName order="surnameFirst" length="short" usage="referring" formality="formal">
			<namePattern draft="unconfirmed">{surname} {given-initial}{given2-initial}</namePattern>
		</personName>
		<personName order="surnameFirst" length="short" usage="referring" formality="informal">
			<namePattern draft="unconfirmed">{surname} {given-initial}</namePattern>
		</personName>
		<personName order="surnameFirst" length="short" usage="addressing" formality="formal">
			<namePattern draft="unconfirmed">{title} {surname}</namePattern>
		</personName>
		<personName order="surnameFirst" length="short" usage="addressing" formality="informal">
			<namePattern draft="unconfirmed">{given-informal}</namePattern>
		</personName>
		<personName order="surnameFirst" length="short" usage="monogram" formality="formal">
			<namePattern draft="unconfirmed">{surname-monogram-allCaps}</namePattern>
		</personName>
		<personName order="surnameFirst" length="short" usage="monogram" formality="informal">
			<namePattern draft="unconfirmed">{given-informal-monogram-allCaps}</namePattern>
		</personName>
		<personName order="sorting" length="long" usage="referring" formality="formal">
			<namePattern draft="unconfirmed">{surname-core}, {given}</namePattern>
		</personName>
		<personName order="sorting" length="long" usage="referring" formality="informal">
			<namePattern draft="unconfirmed">{surname}, {given-informal}</namePattern>
		</personName>
		<personName order="sorting" length="medium" usage="referring" formality="formal">
			<namePattern draft="unconfirmed">{surname-core}, {given} {given2-initial} {surname-prefix}</namePattern>
		</personName>
		<personName order="sorting" length="medium" usage="referring" formality="informal">
			<namePattern draft="unconfirmed">{surname}, {given-informal}</namePattern>
		</personName>
		<personName order="sorting" length="short" usage="referring" formality="formal">
			<namePattern draft="unconfirmed">{surname-core}, {given-initial}{given2-initial} {surname-prefix}</namePattern>
		</personName>
		<personName order="sorting" length="short" usage="referring" formality="informal">
			<namePattern draft="unconfirmed">{surname}, {given-informal}</namePattern>
		</personName>
		<sampleName item="nativeG">
			<nameField type="given" draft="unconfirmed">Jurriey</nameField>
		</sampleName>
		<sampleName item="nativeGS">
			<nameField type="given" draft="unconfirmed">Jurriey</nameField>
			<nameField type="surname" draft="unconfirmed">Martina</nameField>
		</sampleName>
		<sampleName item="nativeGGS">
			<nameField type="given" draft="unconfirmed">Mari-Sue</nameField>
			<nameField type="given2" draft="unconfirmed">Matilda</nameField>
			<nameField type="surname" draft="unconfirmed">Martha</nameField>
		</sampleName>
		<sampleName item="nativeFull">
			<nameField type="title" draft="unconfirmed">sr.</nameField>
			<nameField type="given" draft="unconfirmed">Jackson Martina</nameField>
			<nameField type="given-informal" draft="unconfirmed">Sontje</nameField>
			<nameField type="given2" draft="unconfirmed">Henry Robert</nameField>
			<nameField type="surname-prefix" draft="unconfirmed">∅∅∅</nameField>
			<nameField type="surname-core" draft="unconfirmed">Martha</nameField>
			<nameField type="surname2" draft="unconfirmed">Vapor</nameField>
			<nameField type="generation" draft="unconfirmed">Jr.</nameField>
			<nameField type="credentials" draft="unconfirmed">MP</nameField>
		</sampleName>
		<sampleName item="foreignG">
			<nameField type="given" draft="unconfirmed">Johnny</nameField>
		</sampleName>
		<sampleName item="foreignGS">
			<nameField type="given" draft="unconfirmed">Käthe</nameField>
			<nameField type="surname" draft="unconfirmed">Müller</nameField>
		</sampleName>
		<sampleName item="foreignGGS">
			<nameField type="given" draft="unconfirmed">Zäzilia</nameField>
			<nameField type="given2" draft="unconfirmed">Hamish</nameField>
			<nameField type="surname" draft="unconfirmed">Stöber</nameField>
		</sampleName>
		<sampleName item="foreignFull">
			<nameField type="title" draft="unconfirmed">Prof. Dr.</nameField>
			<nameField type="given" draft="unconfirmed">Ada Kornelia</nameField>
			<nameField type="given-informal" draft="unconfirmed">Neele</nameField>
			<nameField type="given2" draft="unconfirmed">César Martín</nameField>
			<nameField type="surname-prefix" draft="unconfirmed">von</nameField>
			<nameField type="surname-core" draft="unconfirmed">Brühl</nameField>
			<nameField type="surname2" draft="unconfirmed">González Domingo</nameField>
			<nameField type="generation" draft="unconfirmed">Jr.</nameField>
			<nameField type="credentials" draft="unconfirmed">MD DDS</nameField>
		</sampleName>
	</personNames>
</ldml>
